webp2png/__init__.py
webp2png/__main__.py
webp2png/webp2png.py
webp2png-0.1.3.dist-info/METADATA
webp2png-0.1.3.dist-info/WHEEL
webp2png-0.1.3.dist-info/entry_points.txt
webp2png-0.1.3.dist-info/RECORD
