Metadata-Version: 2.1
Name: webp2png
Version: 0.1.3
Summary: webp convert to  png
Home-page: https://github.com/fengtwo0/webp2png
Author: zhaifengtwo
Author-email: zhaifengtwo@gmail.com
Requires-Python: >=3.8,<4.0
Classifier: Programming Language :: Python :: 3
Classifier: Programming Language :: Python :: 3.8
Classifier: Programming Language :: Python :: 3.9
Classifier: Programming Language :: Python :: 3.10
Classifier: Programming Language :: Python :: 3.11
Classifier: Programming Language :: Python :: 3.12
Requires-Dist: pillow (>=10.2.0,<11.0.0)
Project-URL: Repository, https://github.com/fengtwo0/webp2png
